{
  "presentationTable" : {
    "name" : "Document Details",
    "tags" : [ "Project:Fusion Analytics Warehouse - Accounts Payable", "Project:Oracle Analytics for Fusion Financials" ],
    "presentationColumns" : [ {
      "name" : "Invoice Number",
      "tags" : [ "Project:Fusion Analytics Warehouse - Accounts Payable", "Project:Oracle Analytics for Fusion Financials" ],
      "sourceLogicalColumn" : "logicalColumn:Core.Dim - AP Invoice Details.Invoice Number",
      "localization" : {
        "localizationKey" : "Invoice Number",
        "nameVariable" : "VALUEOF(NQ_SESSION.CN_Financials_-_AP_Invoices_Invoice_Details_Invoice_Number)",
        "descriptionVariable" : "VALUEOF(NQ_SESSION.CD_Financials_-_AP_Invoices_Invoice_Details_Invoice_Number)"
      }
    }, {
      "name" : "Invoice Identifier",
      "tags" : [ "Project:Fusion Analytics Warehouse - Accounts Payable", "Project:Oracle Analytics for Fusion Financials" ],
      "sourceLogicalColumn" : "logicalColumn:Core.Dim - AP Invoice Details.Invoice Identifier",
      "localization" : {
        "localizationKey" : "Invoice Identifier",
        "nameVariable" : "VALUEOF(NQ_SESSION.CN_Financials_-_AP_Invoices_Document_Details_Invoice_Identifier)",
        "descriptionVariable" : "VALUEOF(NQ_SESSION.CD_Financials_-_AP_Invoices_Document_Details_Invoice_Identifier)"
      }
    }, {
      "name" : "Invoice Description",
      "tags" : [ "Project:Fusion Analytics Warehouse - Accounts Payable", "Project:Oracle Analytics for Fusion Financials" ],
      "sourceLogicalColumn" : "logicalColumn:Core.Dim - AP Invoice Details.Invoice Description",
      "localization" : {
        "localizationKey" : "Invoice Description",
        "nameVariable" : "VALUEOF(NQ_SESSION.CN_Financials_-_AP_Invoices_Invoice_Details_Invoice_Description)",
        "descriptionVariable" : "VALUEOF(NQ_SESSION.CD_Financials_-_AP_Invoices_Invoice_Details_Invoice_Description)"
      }
    }, {
      "name" : "Invoice Received Date",
      "tags" : [ "Project:Fusion Analytics Warehouse - Accounts Payable", "Project:Oracle Analytics for Fusion Financials" ],
      "sourceLogicalColumn" : "logicalColumn:Core.Dim - AP Invoice Details.Invoice Received Date",
      "localization" : {
        "localizationKey" : "Invoice Received Date",
        "nameVariable" : "VALUEOF(NQ_SESSION.CN_Financials_-_AP_Invoices_Document_Details_Invoice_Received_Date)",
        "descriptionVariable" : "VALUEOF(NQ_SESSION.CD_Financials_-_AP_Invoices_Document_Details_Invoice_Received_Date)"
      }
    }, {
      "name" : "Invoice Currency",
      "tags" : [ "Project:Fusion Analytics Warehouse - Accounts Payable", "Project:Oracle Analytics for Fusion Financials" ],
      "sourceLogicalColumn" : "logicalColumn:Core.Dim - AP Invoice Details.Invoice Currency",
      "localization" : {
        "localizationKey" : "Invoice Currency",
        "nameVariable" : "VALUEOF(NQ_SESSION.CN_Financials_-_AP_Invoices_Document_Details_Invoice_Currency)",
        "descriptionVariable" : "VALUEOF(NQ_SESSION.CD_Financials_-_AP_Invoices_Document_Details_Invoice_Currency)"
      }
    }, {
      "name" : "Invoice Cancelled Indicator",
      "tags" : [ "Project:Fusion Analytics Warehouse - Accounts Payable", "Project:Oracle Analytics for Fusion Financials" ],
      "sourceLogicalColumn" : "logicalColumn:Core.Dim - AP Invoice Details.Invoice Cancelled Indicator",
      "localization" : {
        "localizationKey" : "Invoice Cancelled Indicator",
        "nameVariable" : "VALUEOF(NQ_SESSION.CN_Financials_-_AP_Invoices_Invoice_Details_Invoice_Cancelled_Indicator)",
        "descriptionVariable" : "VALUEOF(NQ_SESSION.CD_Financials_-_AP_Invoices_Invoice_Details_Invoice_Cancelled_Indicator)"
      }
    }, {
      "name" : "Approval Status Code",
      "tags" : [ "Project:Fusion Analytics Warehouse - Accounts Payable", "Project:Oracle Analytics for Fusion Financials" ],
      "sourceLogicalColumn" : "logicalColumn:Core.Dim - AP Approval Status.Approval Status Code",
      "hideIfTrue" : {
        "expressionTemplate" : "1 = 1"
      },
      "localization" : {
        "localizationKey" : "Approval Status Code",
        "nameVariable" : "VALUEOF(NQ_SESSION.CN_Financials_-_AP_Invoices_Document_Details_Approval_Status_Code)",
        "descriptionVariable" : "VALUEOF(NQ_SESSION.CD_Financials_-_AP_Invoices_Document_Details_Approval_Status_Code)"
      }
    }, {
      "name" : "Approval Status Name",
      "tags" : [ "Project:Fusion Analytics Warehouse - Accounts Payable", "Project:Oracle Analytics for Fusion Financials" ],
      "sourceLogicalColumn" : "logicalColumn:Core.Dim - AP Approval Status.Approval Status Name",
      "localization" : {
        "localizationKey" : "Approval Status Name",
        "nameVariable" : "VALUEOF(NQ_SESSION.CN_Financials_-_AP_Invoices_Document_Details_Approval_Status_Name)",
        "descriptionVariable" : "VALUEOF(NQ_SESSION.CD_Financials_-_AP_Invoices_Document_Details_Approval_Status_Name)"
      }
    }, {
      "name" : "Validation Status Code",
      "tags" : [ "Project:Fusion Analytics Warehouse - Accounts Payable", "Project:Oracle Analytics for Fusion Financials" ],
      "sourceLogicalColumn" : "logicalColumn:Core.Dim - AP Validation Status.Validation Status Code",
      "hideIfTrue" : {
        "expressionTemplate" : "1 = 1"
      },
      "localization" : {
        "localizationKey" : "Validation Status Code",
        "nameVariable" : "VALUEOF(NQ_SESSION.CN_Financials_-_AP_Invoices_Document_Details_Validation_Status_Code)",
        "descriptionVariable" : "VALUEOF(NQ_SESSION.CD_Financials_-_AP_Invoices_Document_Details_Validation_Status_Code)"
      }
    }, {
      "name" : "Validation Status Name",
      "tags" : [ "Project:Fusion Analytics Warehouse - Accounts Payable", "Project:Oracle Analytics for Fusion Financials" ],
      "sourceLogicalColumn" : "logicalColumn:Core.Dim - AP Validation Status.Validation Status Name",
      "localization" : {
        "localizationKey" : "Validation Status Name",
        "nameVariable" : "VALUEOF(NQ_SESSION.CN_Financials_-_AP_Invoices_Document_Details_Validation_Status_Name)",
        "descriptionVariable" : "VALUEOF(NQ_SESSION.CD_Financials_-_AP_Invoices_Document_Details_Validation_Status_Name)"
      }
    }, {
      "name" : "Installment Number",
      "tags" : [ "Project:Fusion Analytics Warehouse - Accounts Payable", "Project:Oracle Analytics for Fusion Financials" ],
      "sourceLogicalColumn" : "logicalColumn:Core.Dim - AP Invoice Schedule.Invoice Schedule Number",
      "localization" : {
        "localizationKey" : "Installment Number",
        "nameVariable" : "VALUEOF(NQ_SESSION.CN_Financials_-_AP_Invoices_Document_Details_Installment_Number)",
        "descriptionVariable" : "VALUEOF(NQ_SESSION.CD_Financials_-_AP_Invoices_Document_Details_Installment_Number)"
      }
    }, {
      "name" : "Installment Hold Indicator",
      "tags" : [ "Project:Fusion Analytics Warehouse - Accounts Payable", "Project:Oracle Analytics for Fusion Financials" ],
      "sourceLogicalColumn" : "logicalColumn:Core.Dim - AP Invoice Schedule.Installment Hold Indicator",
      "localization" : {
        "localizationKey" : "Installment Hold Indicator",
        "nameVariable" : "VALUEOF(NQ_SESSION.CN_Financials_-_AP_Invoices_Document_Details_Installment_Hold_Indicator)",
        "descriptionVariable" : "VALUEOF(NQ_SESSION.CD_Financials_-_AP_Invoices_Document_Details_Installment_Hold_Indicator)"
      }
    }, {
      "name" : "Invoice Group",
      "tags" : [ "Project:Fusion Analytics Warehouse - Accounts Payable", "Project:Oracle Analytics for Fusion Financials" ],
      "sourceLogicalColumn" : "logicalColumn:Core.Dim - AP Invoice Details.Invoice Group",
      "localization" : {
        "localizationKey" : "Invoice Group",
        "nameVariable" : "VALUEOF(NQ_SESSION.CN_Financials_-_AP_Invoices_Document_Details_Invoice_Group)",
        "descriptionVariable" : "VALUEOF(NQ_SESSION.CD_Financials_-_AP_Invoices_Document_Details_Invoice_Group)"
      }
    }, {
      "name" : "Liability Account Combination",
      "tags" : [ "Project:Fusion Analytics Warehouse - Accounts Payable", "Project:Oracle Analytics for Fusion Financials" ],
      "sourceLogicalColumn" : "logicalColumn:Core.Dim - Liability Account.Liability Account Combination",
      "localization" : {
        "localizationKey" : "Liability Account Combination",
        "nameVariable" : "VALUEOF(NQ_SESSION.CN_Financials_-_AP_Invoices_Document_Details_Liability_Account_Combination)",
        "descriptionVariable" : "VALUEOF(NQ_SESSION.CD_Financials_-_AP_Invoices_Document_Details_Liability_Account_Combination)"
      }
    }, {
      "name" : "Voucher Number",
      "tags" : [ "Project:Fusion Analytics Warehouse - Accounts Payable", "Project:Oracle Analytics for Fusion Financials" ],
      "sourceLogicalColumn" : "logicalColumn:Core.Dim - AP Invoice Details.Voucher Number",
      "localization" : {
        "localizationKey" : "Voucher Number",
        "nameVariable" : "VALUEOF(NQ_SESSION.CN_Financials_-_AP_Invoices_Document_Details_Voucher_Number)",
        "descriptionVariable" : "VALUEOF(NQ_SESSION.CD_Financials_-_AP_Invoices_Document_Details_Voucher_Number)"
      }
    } ],
    "localization" : {
      "localizationKey" : "Document Details",
      "nameVariable" : "VALUEOF(NQ_SESSION.CN_Financials_-_AP_Invoices_Document_Details)",
      "descriptionVariable" : "VALUEOF(NQ_SESSION.CD_Financials_-_AP_Invoices_Document_Details)"
    }
  }
}