{
  "physicalTable" : {
    "name" : "DW_MANAGER_CF_DH",
    "sourceType" : "TABLE",
    "physicalColumns" : [ {
      "name" : "PERSON_ID",
      "dataType" : "NUMERIC",
      "length" : 0,
      "nullable" : true
    }, {
      "name" : "LEVEL9_MANAGER_ID",
      "dataType" : "NUMERIC",
      "length" : 0,
      "nullable" : true
    }, {
      "name" : "LEVEL9_MANAGER_ASSIGNMENT_ID",
      "dataType" : "NUMERIC",
      "length" : 0,
      "nullable" : true
    }, {
      "name" : "LEVEL8_MANAGER_ID",
      "dataType" : "NUMERIC",
      "length" : 0,
      "nullable" : true
    }, {
      "name" : "LEVEL8_MANAGER_ASSIGNMENT_ID",
      "dataType" : "NUMERIC",
      "length" : 0,
      "nullable" : true
    }, {
      "name" : "LEVEL7_MANAGER_ID",
      "dataType" : "NUMERIC",
      "length" : 0,
      "nullable" : true
    }, {
      "name" : "LEVEL7_MANAGER_ASSIGNMENT_ID",
      "dataType" : "NUMERIC",
      "length" : 0,
      "nullable" : true
    }, {
      "name" : "LEVEL6_MANAGER_ID",
      "dataType" : "NUMERIC",
      "length" : 0,
      "nullable" : true
    }, {
      "name" : "LEVEL6_MANAGER_ASSIGNMENT_ID",
      "dataType" : "NUMERIC",
      "length" : 0,
      "nullable" : true
    }, {
      "name" : "LEVEL5_MANAGER_ID",
      "dataType" : "NUMERIC",
      "length" : 0,
      "nullable" : true
    }, {
      "name" : "LEVEL5_MANAGER_ASSIGNMENT_ID",
      "dataType" : "NUMERIC",
      "length" : 0,
      "nullable" : true
    }, {
      "name" : "LEVEL4_MANAGER_ID",
      "dataType" : "NUMERIC",
      "length" : 0,
      "nullable" : true
    }, {
      "name" : "LEVEL4_MANAGER_ASSIGNMENT_ID",
      "dataType" : "NUMERIC",
      "length" : 0,
      "nullable" : true
    }, {
      "name" : "LEVEL3_MANAGER_ID",
      "dataType" : "NUMERIC",
      "length" : 0,
      "nullable" : true
    }, {
      "name" : "LEVEL3_MANAGER_ASSIGNMENT_ID",
      "dataType" : "NUMERIC",
      "length" : 0,
      "nullable" : true
    }, {
      "name" : "LEVEL2_MANAGER_ID",
      "dataType" : "NUMERIC",
      "length" : 0,
      "nullable" : true
    }, {
      "name" : "LEVEL2_MANAGER_ASSIGNMENT_ID",
      "dataType" : "NUMERIC",
      "length" : 0,
      "nullable" : true
    }, {
      "name" : "LEVEL1_MANAGER_ID",
      "dataType" : "NUMERIC",
      "length" : 0,
      "nullable" : true
    }, {
      "name" : "LEVEL1_MANAGER_ASSIGNMENT_ID",
      "dataType" : "NUMERIC",
      "length" : 0,
      "nullable" : true
    }, {
      "name" : "LEVEL15_MANAGER_ID",
      "dataType" : "NUMERIC",
      "length" : 0,
      "nullable" : true
    }, {
      "name" : "LEVEL15_MANAGER_ASSIGNMENT_ID",
      "dataType" : "NUMERIC",
      "length" : 0,
      "nullable" : true
    }, {
      "name" : "LEVEL14_MANAGER_ID",
      "dataType" : "NUMERIC",
      "length" : 0,
      "nullable" : true
    }, {
      "name" : "LEVEL14_MANAGER_ASSIGNMENT_ID",
      "dataType" : "NUMERIC",
      "length" : 0,
      "nullable" : true
    }, {
      "name" : "LEVEL13_MANAGER_ID",
      "dataType" : "NUMERIC",
      "length" : 0,
      "nullable" : true
    }, {
      "name" : "LEVEL13_MANAGER_ASSIGNMENT_ID",
      "dataType" : "NUMERIC",
      "length" : 0,
      "nullable" : true
    }, {
      "name" : "LEVEL12_MANAGER_ID",
      "dataType" : "NUMERIC",
      "length" : 0,
      "nullable" : true
    }, {
      "name" : "LEVEL12_MANAGER_ASSIGNMENT_ID",
      "dataType" : "NUMERIC",
      "length" : 0,
      "nullable" : true
    }, {
      "name" : "LEVEL11_MANAGER_ID",
      "dataType" : "NUMERIC",
      "length" : 0,
      "nullable" : true
    }, {
      "name" : "LEVEL11_MANAGER_ASSIGNMENT_ID",
      "dataType" : "NUMERIC",
      "length" : 0,
      "nullable" : true
    }, {
      "name" : "LEVEL10_MANAGER_ID",
      "dataType" : "NUMERIC",
      "length" : 0,
      "nullable" : true
    }, {
      "name" : "LEVEL10_MANAGER_ASSIGNMENT_ID",
      "dataType" : "NUMERIC",
      "length" : 0,
      "nullable" : true
    }, {
      "name" : "EFFECTIVE_END_DATE",
      "dataType" : "DATE",
      "length" : 0,
      "nullable" : true
    }, {
      "name" : "EFFECTIVE_START_DATE",
      "dataType" : "DATE",
      "length" : 0,
      "nullable" : true
    }, {
      "name" : "ASSIGNMENT_ID",
      "dataType" : "NUMERIC",
      "length" : 0,
      "nullable" : true
    } ],
    "additionalKeys" : [ [ "ASSIGNMENT_ID", "EFFECTIVE_START_DATE", "EFFECTIVE_END_DATE" ] ],
    "caching" : {
      "enable" : true,
      "expiryTime" : 0
    }
  }
}