{
  "physicalTable" : {
    "name" : "DW_TNL_PRSCD_TM_ENTRY_EF",
    "sourceType" : "TABLE",
    "physicalColumns" : [ {
      "name" : "BARGAINING_UNIT_CODE",
      "dataType" : "VARCHAR",
      "length" : 32,
      "nullable" : true
    }, {
      "name" : "TENURE_IN_YEARS",
      "dataType" : "DOUBLE",
      "length" : 0,
      "nullable" : true
    }, {
      "name" : "AGE_IN_YEARS",
      "dataType" : "DOUBLE",
      "length" : 0,
      "nullable" : true
    }, {
      "name" : "SEX",
      "dataType" : "VARCHAR",
      "length" : 32,
      "nullable" : true
    }, {
      "name" : "LEGISLATION_CODE",
      "dataType" : "VARCHAR",
      "length" : 256,
      "nullable" : true
    }, {
      "name" : "MANAGER_ID",
      "dataType" : "NUMERIC",
      "length" : 0,
      "nullable" : true
    }, {
      "name" : "MANAGER_ASSIGNMENT_ID",
      "dataType" : "NUMERIC",
      "length" : 0,
      "nullable" : true
    }, {
      "name" : "BUSINESS_UNIT_ID",
      "dataType" : "NUMERIC",
      "length" : 0,
      "nullable" : true
    }, {
      "name" : "LEGAL_EMPLOYER_ID",
      "dataType" : "NUMERIC",
      "length" : 0,
      "nullable" : true
    }, {
      "name" : "GRADE_ID",
      "dataType" : "NUMERIC",
      "length" : 0,
      "nullable" : true
    }, {
      "name" : "POSITION_ID",
      "dataType" : "NUMERIC",
      "length" : 0,
      "nullable" : true
    }, {
      "name" : "LOCATION_ID",
      "dataType" : "NUMERIC",
      "length" : 0,
      "nullable" : true
    }, {
      "name" : "JOB_ID",
      "dataType" : "NUMERIC",
      "length" : 0,
      "nullable" : true
    }, {
      "name" : "REPORTING_ESTABLISHMENT_ID",
      "dataType" : "NUMERIC",
      "length" : 0,
      "nullable" : true
    }, {
      "name" : "DEPARTMENT_ID",
      "dataType" : "NUMERIC",
      "length" : 0,
      "nullable" : true
    }, {
      "name" : "DAY_STOP_TIME",
      "dataType" : "TIMESTAMP",
      "length" : 0,
      "nullable" : true
    }, {
      "name" : "DAY_START_TIME",
      "dataType" : "TIMESTAMP",
      "length" : 0,
      "nullable" : true
    }, {
      "name" : "LAYOUT_SET_ID",
      "dataType" : "NUMERIC",
      "length" : 0,
      "nullable" : true
    }, {
      "name" : "TMCRD_LAYER_CODE",
      "dataType" : "VARCHAR",
      "length" : 32,
      "nullable" : true
    }, {
      "name" : "TMCRD_DELETE_FLAG",
      "dataType" : "VARCHAR",
      "length" : 16,
      "nullable" : true
    }, {
      "name" : "TMCRD_STOP_TIME",
      "dataType" : "TIMESTAMP",
      "length" : 0,
      "nullable" : true
    }, {
      "name" : "TMCRD_START_TIME",
      "dataType" : "TIMESTAMP",
      "length" : 0,
      "nullable" : true
    }, {
      "name" : "ABSENCE_TYPE_ID",
      "dataType" : "NUMERIC",
      "length" : 0,
      "nullable" : true
    }, {
      "name" : "COMP_ABSENCE_PLAN_ID",
      "dataType" : "NUMERIC",
      "length" : 0,
      "nullable" : true
    }, {
      "name" : "PAY_PAYROLL_TIME_TYPE",
      "dataType" : "VARCHAR",
      "length" : 128,
      "nullable" : true
    }, {
      "name" : "DOCUMENT_TYPE",
      "dataType" : "VARCHAR",
      "length" : 128,
      "nullable" : true
    }, {
      "name" : "EXPENDITURE_TYPE_ID",
      "dataType" : "NUMERIC",
      "length" : 0,
      "nullable" : true
    }, {
      "name" : "WORK_TYPE_ID",
      "dataType" : "NUMERIC",
      "length" : 0,
      "nullable" : true
    }, {
      "name" : "PROJECT_UNIT_ID",
      "dataType" : "NUMERIC",
      "length" : 0,
      "nullable" : true
    }, {
      "name" : "TASK_ID",
      "dataType" : "NUMERIC",
      "length" : 0,
      "nullable" : true
    }, {
      "name" : "PROJECT_ID",
      "dataType" : "NUMERIC",
      "length" : 0,
      "nullable" : true
    }, {
      "name" : "BILLABLE_FLAG",
      "dataType" : "VARCHAR",
      "length" : 16,
      "nullable" : true
    }, {
      "name" : "TIME_REPORTER_ID",
      "dataType" : "NUMERIC",
      "length" : 0,
      "nullable" : true
    }, {
      "name" : "ASSIGNMENT_ID",
      "dataType" : "NUMERIC",
      "length" : 0,
      "nullable" : true
    }, {
      "name" : "PERSON_ID",
      "dataType" : "NUMERIC",
      "length" : 0,
      "nullable" : true
    }, {
      "name" : "LAYER_CODE",
      "dataType" : "VARCHAR",
      "length" : 32,
      "nullable" : true
    }, {
      "name" : "STOP_TIME",
      "dataType" : "TIMESTAMP",
      "length" : 0,
      "nullable" : true
    }, {
      "name" : "START_TIME",
      "dataType" : "TIMESTAMP",
      "length" : 0,
      "nullable" : true
    }, {
      "name" : "MEASURE",
      "dataType" : "DOUBLE",
      "length" : 0,
      "nullable" : true
    }, {
      "name" : "UNIT_OF_MEASURE",
      "dataType" : "VARCHAR",
      "length" : 32,
      "nullable" : true
    }, {
      "name" : "TM_REC_TYPE",
      "dataType" : "VARCHAR",
      "length" : 32,
      "nullable" : true
    }, {
      "name" : "TMCRD_TM_REC_GRP_VERSION",
      "dataType" : "NUMERIC",
      "length" : 0,
      "nullable" : true
    }, {
      "name" : "TMCRD_TM_REC_GRP_ID",
      "dataType" : "NUMERIC",
      "length" : 0,
      "nullable" : true
    }, {
      "name" : "DAY_TM_REC_GRP_VERSION",
      "dataType" : "NUMERIC",
      "length" : 0,
      "nullable" : true
    }, {
      "name" : "DAY_TM_REC_GRP_ID",
      "dataType" : "NUMERIC",
      "length" : 0,
      "nullable" : true
    }, {
      "name" : "TM_REC_VERSION",
      "dataType" : "NUMERIC",
      "length" : 0,
      "nullable" : true
    }, {
      "name" : "ANCHOR_DATE",
      "dataType" : "DATE",
      "length" : 0,
      "nullable" : true
    }, {
      "name" : "TM_REC_ID",
      "dataType" : "NUMERIC",
      "length" : 0,
      "nullable" : true
    }, {
      "name" : "REPEATING_TIME_PERIOD_ID",
      "dataType" : "NUMERIC",
      "length" : 0,
      "nullable" : true
    }, {
      "name" : "DAY_DELETE_FLAG",
      "dataType" : "VARCHAR",
      "length" : 16,
      "nullable" : true
    }, {
      "name" : "ORIG_TM_REC_VERSION",
      "dataType" : "NUMERIC",
      "length" : 0,
      "nullable" : false
    }, {
      "name" : "ORIG_TM_REC_ID",
      "dataType" : "NUMERIC",
      "length" : 0,
      "nullable" : true
    }, {
      "name" : "DELETE_FLAG",
      "dataType" : "VARCHAR",
      "length" : 16,
      "nullable" : true
    } ],
    "additionalKeys" : [ [ "TM_REC_ID" ] ],
    "caching" : {
      "enable" : true,
      "expiryTime" : 0
    }
  }
}